./.gitignore
./LICENSE
./PKG-INFO
./README.md
./__init__.py
./api_clients.py
./bluesky_search.py
./pyproject.toml
./reddit_search.py
./search_assistant.py
./socialsearch_cli.py
vociro-0.1.2.dist-info/METADATA
vociro-0.1.2.dist-info/WHEEL
vociro-0.1.2.dist-info/entry_points.txt
vociro-0.1.2.dist-info/licenses/LICENSE
vociro-0.1.2.dist-info/RECORD
