Metadata-Version: 2.4
Name: vociro
Version: 0.1.2
Summary: Multisource social-media search assistant for sentiment analysis (Reddit, Bluesky, optional Web).
Author-email: Your Name <you@example.com>
License: MIT
License-File: LICENSE
Requires-Python: >=3.9
Requires-Dist: openai>=1.13
Requires-Dist: python-dotenv>=1.0
Requires-Dist: requests>=2.31
Requires-Dist: rich>=13.7
